{"type":"FeatureCollection","features":[{"type":"Feature","properties":{"name":"الخرج","parent":"22835047,NAVTEQ","officialNames":{"ar":"الخرج"}},"geometry":{"type":"Point","coordinates":[47.30421,24.16726]},"id":"C22848129,NAVTEQ"},{"type":"Feature","properties":{"name":"الطائف","parent":"21424631,NAVTEQ","officialNames":{"ar":"الطائف"}},"geometry":{"type":"Point","coordinates":[40.42409,21.27975]},"id":"C21487731,NAVTEQ"},{"type":"Feature","properties":{"name":"القطيف","parent":"21426747,NAVTEQ","officialNames":{"ar":"القطيف"}},"geometry":{"type":"Point","coordinates":[50.00642,26.5675]},"id":"C21479843,NAVTEQ"},{"type":"Feature","properties":{"name":"الرس","parent":"23490173,NAVTEQ","officialNames":{"ar":"الرس"}},"geometry":{"type":"Point","coordinates":[43.48929,25.86689]},"id":"C23414468,NAVTEQ"},{"type":"Feature","properties":{"name":"خميس مشيط","parent":"22486844,NAVTEQ","officialNames":{"ar":"خميس مشيط"}},"geometry":{"type":"Point","coordinates":[42.69067,18.3025]},"id":"C23369629,NAVTEQ"},{"type":"Feature","properties":{"name":"الأحساء","parent":"21426747,NAVTEQ","officialNames":{"ar":"الأحساء"}},"geometry":{"type":"Point","coordinates":[49.58791,25.36818]},"id":"C21480544,NAVTEQ"},{"type":"Feature","properties":{"name":"حائل","parent":"21480926,NAVTEQ","officialNames":{"ar":"حائل"}},"geometry":{"type":"Point","coordinates":[41.69811,27.45974]},"id":"C21570355,NAVTEQ"},{"type":"Feature","properties":{"name":"نجران","parent":"21480924,NAVTEQ","officialNames":{"ar":"نجران"}},"geometry":{"type":"Point","coordinates":[44.2601,17.54877]},"id":"C21570359,NAVTEQ"},{"type":"Feature","properties":{"name":"الجبيل","parent":"21426747,NAVTEQ","officialNames":{"ar":"الجبيل"}},"geometry":{"type":"Point","coordinates":[49.65431,27.01308]},"id":"C21480540,NAVTEQ"},{"type":"Feature","properties":{"name":"صامطة","parent":"23339020,NAVTEQ","officialNames":{"ar":"صامطة"}},"geometry":{"type":"Point","coordinates":[42.9158,16.58386]},"id":"C23339175,NAVTEQ"},{"type":"Feature","properties":{"name":"جدة","parent":"21424631,NAVTEQ","officialNames":{"de":"Djidda","da":"Jedda","no":"Jiddah","fr":"Djedda","sv":"Jiddah","ar":"جدة","en":"Jiddah"}},"geometry":{"type":"Point","coordinates":[39.18286,21.48168]},"id":"C21424642,NAVTEQ"},{"type":"Feature","properties":{"name":"ينبع","parent":"22639275,NAVTEQ","officialNames":{"ar":"ينبع"}},"geometry":{"type":"Point","coordinates":[38.10701,24.07061]},"id":"C22639277,NAVTEQ"},{"type":"Feature","properties":{"name":"عنيزة","parent":"21480917,NAVTEQ","officialNames":{"ar":"عنيزة"}},"geometry":{"type":"Point","coordinates":[43.99386,26.09657]},"id":"C23330166,NAVTEQ"},{"type":"Feature","properties":{"name":"القريات","parent":"23330164,NAVTEQ","officialNames":{"ar":"القريات"}},"geometry":{"type":"Point","coordinates":[37.34496,31.33062]},"id":"C23330167,NAVTEQ"},{"type":"Feature","properties":{"name":"القنفذة","parent":"23383923,NAVTEQ","officialNames":{"ar":"القنفذة"}},"geometry":{"type":"Point","coordinates":[41.08933,19.13351]},"id":"C23383932,NAVTEQ"},{"type":"Feature","properties":{"name":"حفر الباطن","parent":"21426747,NAVTEQ","officialNames":{"ar":"حفر الباطن"}},"geometry":{"type":"Point","coordinates":[45.9722,28.4341]},"id":"C23010894,NAVTEQ"},{"type":"Feature","properties":{"name":"ابو عريش","parent":"23330159,NAVTEQ","officialNames":{"ar":"ابو عريش"}},"geometry":{"type":"Point","coordinates":[42.83088,16.96872]},"id":"C23330161,NAVTEQ"},{"type":"Feature","properties":{"name":"صبيا","parent":"23330158,NAVTEQ","officialNames":{"ar":"صبيا"}},"geometry":{"type":"Point","coordinates":[42.62654,17.14894]},"id":"C23330162,NAVTEQ"},{"type":"Feature","properties":{"name":"سكاكا","parent":"23330160,NAVTEQ","officialNames":{"ar":"سكاكا"}},"geometry":{"type":"Point","coordinates":[40.22522,29.98049]},"id":"C23330163,NAVTEQ"},{"type":"Feature","properties":{"name":"المدينة","parent":"21454307,NAVTEQ","officialNames":{"de":"Medina","fr":"Médine","ar":"المدينة"}},"geometry":{"type":"Point","coordinates":[39.60664,24.46728]},"id":"C21454308,NAVTEQ"},{"type":"Feature","properties":{"name":"تبوك","parent":"21480937,NAVTEQ","officialNames":{"ar":"تبوك"}},"geometry":{"type":"Point","coordinates":[36.5721,28.38939]},"id":"C21564966,NAVTEQ"},{"type":"Feature","properties":{"name":"محايل","parent":"23369350,NAVTEQ","officialNames":{"ar":"محايل"}},"geometry":{"type":"Point","coordinates":[42.04736,18.54628]},"id":"C23369365,NAVTEQ"},{"type":"Feature","properties":{"name":"بيشة","parent":"23369346,NAVTEQ","officialNames":{"ar":"بيشة"}},"geometry":{"type":"Point","coordinates":[42.61897,20.01104]},"id":"C23369357,NAVTEQ"},{"type":"Feature","properties":{"name":"الخبر","parent":"21426747,NAVTEQ","officialNames":{"ar":"الخبر"}},"geometry":{"type":"Point","coordinates":[50.21434,26.28665]},"id":"C21426752,NAVTEQ"},{"type":"Feature","properties":{"name":"الليث","parent":"23383924,NAVTEQ","officialNames":{"ar":"الليث"}},"geometry":{"type":"Point","coordinates":[40.28354,20.15301]},"id":"C23310694,NAVTEQ"},{"type":"Feature","properties":{"name":"ابها","parent":"21480918,NAVTEQ","officialNames":{"ar":"ابها"}},"geometry":{"type":"Point","coordinates":[42.50298,18.21606]},"id":"C22486815,NAVTEQ"},{"type":"Feature","properties":{"name":"القويعية","parent":"23352673,NAVTEQ","officialNames":{"ar":"القويعية"}},"geometry":{"type":"Point","coordinates":[45.28617,24.07478]},"id":"C21427645,NAVTEQ"},{"type":"Feature","properties":{"name":"الرياض","parent":"21424222,NAVTEQ","officialNames":{"de":"Riad","it":"Riyad","pt":"Riade","fr":"Riyad","ar":"الرياض","en":"Riyadh","es":"Riad","nl":"Riyad"}},"geometry":{"type":"Point","coordinates":[46.71458,24.64732]},"id":"C21424497,NAVTEQ"},{"type":"Feature","properties":{"name":"مكة","parent":"21424631,NAVTEQ","officialNames":{"de":"Mekka","da":"Mekka","no":"Mekka","fr":"La Mecque","sv":"Mekka","ar":"مكة","en":"Mecca","es":"La Meca"}},"geometry":{"type":"Point","coordinates":[39.82837,21.42973]},"id":"C21454310,NAVTEQ"},{"type":"Feature","properties":{"name":"جازان","parent":"23330154,NAVTEQ","officialNames":{"ar":"جازان"}},"geometry":{"type":"Point","coordinates":[42.55765,16.89152]},"id":"C23330155,NAVTEQ"},{"type":"Feature","properties":{"name":"عرعر","parent":"21480921,NAVTEQ","officialNames":{"ar":"عرعر"}},"geometry":{"type":"Point","coordinates":[41.01554,30.97298]},"id":"C23330152,NAVTEQ"},{"type":"Feature","properties":{"name":"الدوادمي","parent":"23352671,NAVTEQ","officialNames":{"ar":"الدوادمي"}},"geometry":{"type":"Point","coordinates":[44.37407,24.49724]},"id":"C23352676,NAVTEQ"},{"type":"Feature","properties":{"name":"المجمعة","parent":"23352672,NAVTEQ","officialNames":{"ar":"المجمعة"}},"geometry":{"type":"Point","coordinates":[45.3505,25.89765]},"id":"C23352677,NAVTEQ"},{"type":"Feature","properties":{"name":"الدمام","parent":"21426747,NAVTEQ","officialNames":{"fr":"Damman","ar":"الدمام","da":"Al Dammam"}},"geometry":{"type":"Point","coordinates":[50.10461,26.44425]},"id":"C21426748,NAVTEQ"},{"type":"Feature","properties":{"name":"بريدة","parent":"22927526,NAVTEQ","officialNames":{"ar":"بريدة"}},"geometry":{"type":"Point","coordinates":[43.8988,26.40982]},"id":"C22927605,NAVTEQ"}]}