{"type":"FeatureCollection","features":[{"type":"Feature","properties":{"name":"Città del Vaticano","parent":"20147520,NAVTEQ","officialNames":{"sk":"Vatikán","da":"Vatikanstaten","it":"Città del Vaticano","hu":"Vatikánváros","cs":"Vatikán","de":"Vatikanstadt","el":"Κρατος του Βατικανου","fi":"Vatikaani","pt":"Cidade do Vaticano","pl":"Watykan","fr":"Cité du Vatican","sv":"Vatikanstaten","en":"Vatican City","ru":"Ватикан","es":"Ciudad del Vaticano","nl":"Vaticaanstad"}},"geometry":{"type":"Point","coordinates":[12.45826,41.90246]},"id":"C20147521,NAVTEQ"}]}