{"type":"FeatureCollection","features":[{"type":"Feature","properties":{"name":"Maluti A Phofung","parent":"23401250,NAVTEQ","officialNames":{"en":"Maluti A Phofung"}},"geometry":{"type":"Point","coordinates":[28.82446,-28.51597]},"id":"C23401285,NAVTEQ"},{"type":"Feature","properties":{"name":"Randburg","parent":"23402002,NAVTEQ","officialNames":{"en":"Randburg"}},"geometry":{"type":"Point","coordinates":[28.00278,-26.10049]},"id":"C23405931,NAVTEQ"},{"type":"Feature","properties":{"name":"Umlalazi","parent":"23404478,NAVTEQ","officialNames":{"en":"Umlalazi"}},"geometry":{"type":"Point","coordinates":[31.4809,-28.8845]},"id":"C23400408,NAVTEQ"},{"type":"Feature","properties":{"name":"Thulamela","parent":"23404756,NAVTEQ","officialNames":{"en":"Thulamela"}},"geometry":{"type":"Point","coordinates":[30.49066,-22.9717]},"id":"C23402144,NAVTEQ"},{"type":"Feature","properties":{"name":"Greater Tubatse","parent":"23403425,NAVTEQ","officialNames":{"en":"Greater Tubatse"}},"geometry":{"type":"Point","coordinates":[30.56184,-24.74368]},"id":"C23402799,NAVTEQ"},{"type":"Feature","properties":{"name":"Madibeng","parent":"23399630,NAVTEQ","officialNames":{"en":"Madibeng"}},"geometry":{"type":"Point","coordinates":[27.72905,-25.40434]},"id":"C23402507,NAVTEQ"},{"type":"Feature","properties":{"name":"Lepele-Nkumpi","parent":"23400975,NAVTEQ","officialNames":{"en":"Lepele-Nkumpi"}},"geometry":{"type":"Point","coordinates":[29.50894,-24.30158]},"id":"C23403462,NAVTEQ"},{"type":"Feature","properties":{"name":"Engcobo","parent":"23402169,NAVTEQ","officialNames":{"en":"Engcobo"}},"geometry":{"type":"Point","coordinates":[28.00104,-31.67628]},"id":"C23404179,NAVTEQ"},{"type":"Feature","properties":{"name":"Ntabankulu","parent":"23401197,NAVTEQ","officialNames":{"en":"Ntabankulu"}},"geometry":{"type":"Point","coordinates":[29.30222,-30.96116]},"id":"C23404831,NAVTEQ"},{"type":"Feature","properties":{"name":"Emnambithi-Ladysmith","parent":"23404765,NAVTEQ","officialNames":{"en":"Emnambithi-Ladysmith"}},"geometry":{"type":"Point","coordinates":[29.78676,-28.55373]},"id":"C23400489,NAVTEQ"},{"type":"Feature","properties":{"name":"Mbhashe","parent":"23401323,NAVTEQ","officialNames":{"en":"Mbhashe"}},"geometry":{"type":"Point","coordinates":[28.30472,-32.09934]},"id":"C23403340,NAVTEQ"},{"type":"Feature","properties":{"name":"Soweto","parent":"23402002,NAVTEQ","officialNames":{"en":"Soweto"}},"geometry":{"type":"Point","coordinates":[27.9172,-26.23221]},"id":"C23405833,NAVTEQ"},{"type":"Feature","properties":{"name":"Moretele","parent":"23399630,NAVTEQ","officialNames":{"en":"Moretele"}},"geometry":{"type":"Point","coordinates":[28.2383,-25.33611]},"id":"C23401732,NAVTEQ"},{"type":"Feature","properties":{"name":"Mogale City","parent":"23400496,NAVTEQ","officialNames":{"en":"Mogale City"}},"geometry":{"type":"Point","coordinates":[27.7708,-26.10252]},"id":"C23401471,NAVTEQ"},{"type":"Feature","properties":{"name":"Bloemfontein","parent":"23402002,NAVTEQ","officialNames":{"de":"Bloemfontein","fr":"Bloemfontein","en":"Bloemfontein","it":"Bloemfontein","es":"Bloemfontein","nl":"Bloemfontein"}},"geometry":{"type":"Point","coordinates":[26.22533,-29.11345]},"id":"C23405734,NAVTEQ"},{"type":"Feature","properties":{"name":"Johannesburg","parent":"23401543,NAVTEQ","officialNames":{"de":"Johannesburg","it":"Johannesburg","pt":"Joanesburgo","fr":"Johannesburg","en":"Johannesburg","es":"Johannesburgo","nl":"Johannesburg"}},"geometry":{"type":"Point","coordinates":[28.04002,-26.20492]},"id":"C23400800,NAVTEQ"},{"type":"Feature","properties":{"name":"Randfontein","parent":"23400496,NAVTEQ","officialNames":{"en":"Randfontein"}},"geometry":{"type":"Point","coordinates":[27.70644,-26.17333]},"id":"C23402903,NAVTEQ"},{"type":"Feature","properties":{"name":"Lukanji","parent":"23402169,NAVTEQ","officialNames":{"en":"Lukanji"}},"geometry":{"type":"Point","coordinates":[26.97596,-31.95556]},"id":"C23403504,NAVTEQ"},{"type":"Feature","properties":{"name":"Dihlabeng","parent":"23401250,NAVTEQ","officialNames":{"en":"Dihlabeng"}},"geometry":{"type":"Point","coordinates":[28.31863,-28.23229]},"id":"C23400804,NAVTEQ"},{"type":"Feature","properties":{"name":"uMhlabuyalingana","parent":"23402845,NAVTEQ","officialNames":{"en":"uMhlabuyalingana"}},"geometry":{"type":"Point","coordinates":[32.55386,-27.08994]},"id":"C23401257,NAVTEQ"},{"type":"Feature","properties":{"name":"Nkomazi","parent":"23401768,NAVTEQ","officialNames":{"en":"Nkomazi"}},"geometry":{"type":"Point","coordinates":[31.51211,-25.68632]},"id":"C23404574,NAVTEQ"},{"type":"Feature","properties":{"name":"Bhisho","parent":"23401323,NAVTEQ","officialNames":{"de":"Bhisho","fr":"Bisho","en":"Bhisho","it":"Bhisho","es":"Bisho","nl":"Bhisho"}},"geometry":{"type":"Point","coordinates":[27.43903,-32.84335]},"id":"C23403904,NAVTEQ"},{"type":"Feature","properties":{"name":"Pietermaritzburg","parent":"23404131,NAVTEQ","officialNames":{"de":"Pietermaritzburg","fr":"Pietermaritzburg","en":"Pietermaritzburg","it":"Pietermaritzburg","es":"Pietermaritzburg","nl":"Pietermaritzburg"}},"geometry":{"type":"Point","coordinates":[30.37812,-29.60076]},"id":"C23400884,NAVTEQ"},{"type":"Feature","properties":{"name":"Matlosana","parent":"23403718,NAVTEQ","officialNames":{"en":"Matlosana"}},"geometry":{"type":"Point","coordinates":[26.66275,-26.84643]},"id":"C23399568,NAVTEQ"},{"type":"Feature","properties":{"name":"Polokwane","parent":"23400975,NAVTEQ","officialNames":{"de":"Polokwane","fr":"Polokwane","en":"Polokwane","it":"Polokwane","es":"Polokwane","nl":"Polokwane"}},"geometry":{"type":"Point","coordinates":[29.45981,-23.90893]},"id":"C23402314,NAVTEQ"},{"type":"Feature","properties":{"name":"Ramotshere Moiloa","parent":"23403531,NAVTEQ","officialNames":{"en":"Ramotshere Moiloa"}},"geometry":{"type":"Point","coordinates":[26.15309,-25.12369]},"id":"C23402599,NAVTEQ"},{"type":"Feature","properties":{"name":"Govan Mbeki","parent":"23402535,NAVTEQ","officialNames":{"en":"Govan Mbeki"}},"geometry":{"type":"Point","coordinates":[29.19947,-26.51202]},"id":"C23403353,NAVTEQ"},{"type":"Feature","properties":{"name":"Nquthu","parent":"23399640,NAVTEQ","officialNames":{"en":"Nquthu"}},"geometry":{"type":"Point","coordinates":[30.68934,-28.24039]},"id":"C23404668,NAVTEQ"},{"type":"Feature","properties":{"name":"Kimberley","parent":"23402002,NAVTEQ","officialNames":{"en":"Kimberley"}},"geometry":{"type":"Point","coordinates":[24.76023,-28.73444]},"id":"C23405997,NAVTEQ"},{"type":"Feature","properties":{"name":"Moqhaka","parent":"23399730,NAVTEQ","officialNames":{"en":"Moqhaka"}},"geometry":{"type":"Point","coordinates":[27.23441,-27.66531]},"id":"C23404375,NAVTEQ"},{"type":"Feature","properties":{"name":"Port Elizabeth","parent":"23402002,NAVTEQ","officialNames":{"en":"Port Elizabeth"}},"geometry":{"type":"Point","coordinates":[25.62328,-33.9625]},"id":"C23405748,NAVTEQ"},{"type":"Feature","properties":{"name":"Dannhauser","parent":"23400249,NAVTEQ","officialNames":{"en":"Dannhauser"}},"geometry":{"type":"Point","coordinates":[30.08544,-28.00842]},"id":"C23400818,NAVTEQ"},{"type":"Feature","properties":{"name":"Westonaria","parent":"23400496,NAVTEQ","officialNames":{"en":"Westonaria"}},"geometry":{"type":"Point","coordinates":[27.64085,-26.32194]},"id":"C23402262,NAVTEQ"},{"type":"Feature","properties":{"name":"Ubuhlebezwe","parent":"23402283,NAVTEQ","officialNames":{"en":"Ubuhlebezwe"}},"geometry":{"type":"Point","coordinates":[30.06582,-30.14853]},"id":"C23403913,NAVTEQ"},{"type":"Feature","properties":{"name":"Mbonambi","parent":"23404478,NAVTEQ","officialNames":{"en":"Mbonambi"}},"geometry":{"type":"Point","coordinates":[32.13161,-28.53543]},"id":"C23403578,NAVTEQ"},{"type":"Feature","properties":{"name":"Ndwedwe","parent":"23402680,NAVTEQ","officialNames":{"en":"Ndwedwe"}},"geometry":{"type":"Point","coordinates":[30.9861,-29.43182]},"id":"C23401796,NAVTEQ"},{"type":"Feature","properties":{"name":"Greater Giyani","parent":"23404087,NAVTEQ","officialNames":{"en":"Greater Giyani"}},"geometry":{"type":"Point","coordinates":[30.68619,-23.30199]},"id":"C23402872,NAVTEQ"},{"type":"Feature","properties":{"name":"Amahlathi","parent":"23401323,NAVTEQ","officialNames":{"en":"Amahlathi"}},"geometry":{"type":"Point","coordinates":[27.42885,-32.56893]},"id":"C23400067,NAVTEQ"},{"type":"Feature","properties":{"name":"Ditsobotla","parent":"23403531,NAVTEQ","officialNames":{"en":"Ditsobotla"}},"geometry":{"type":"Point","coordinates":[26.16047,-26.15114]},"id":"C23403163,NAVTEQ"},{"type":"Feature","properties":{"name":"Emalahleni","parent":"23402169,NAVTEQ","officialNames":{"en":"Emalahleni"}},"geometry":{"type":"Point","coordinates":[27.04722,-31.37737]},"id":"C23404290,NAVTEQ"},{"type":"Feature","properties":{"name":"Ingwe","parent":"23402283,NAVTEQ","officialNames":{"en":"Ingwe"}},"geometry":{"type":"Point","coordinates":[29.84077,-30.0278]},"id":"C23404207,NAVTEQ"},{"type":"Feature","properties":{"name":"Makhado","parent":"23404756,NAVTEQ","officialNames":{"en":"Makhado"}},"geometry":{"type":"Point","coordinates":[29.90414,-23.04854]},"id":"C23404699,NAVTEQ"},{"type":"Feature","properties":{"name":"Msinga","parent":"23399640,NAVTEQ","officialNames":{"en":"Msinga"}},"geometry":{"type":"Point","coordinates":[30.42374,-28.55109]},"id":"C23403485,NAVTEQ"},{"type":"Feature","properties":{"name":"Centurion","parent":"23402002,NAVTEQ","officialNames":{"en":"Centurion"}},"geometry":{"type":"Point","coordinates":[28.1532,-25.84453]},"id":"C23405714,NAVTEQ"},{"type":"Feature","properties":{"name":"George","parent":"23400507,NAVTEQ","officialNames":{"en":"George"}},"geometry":{"type":"Point","coordinates":[22.47151,-33.9611]},"id":"C23401922,NAVTEQ"},{"type":"Feature","properties":{"name":"Elias Motsoaledi","parent":"23403425,NAVTEQ","officialNames":{"en":"Elias Motsoaledi"}},"geometry":{"type":"Point","coordinates":[29.19907,-25.29743]},"id":"C23403222,NAVTEQ"},{"type":"Feature","properties":{"name":"Intsika Yethu","parent":"23402169,NAVTEQ","officialNames":{"en":"Intsika Yethu"}},"geometry":{"type":"Point","coordinates":[27.58143,-32.00895]},"id":"C23402030,NAVTEQ"},{"type":"Feature","properties":{"name":"Mogalakwena","parent":"23402335,NAVTEQ","officialNames":{"en":"Mogalakwena"}},"geometry":{"type":"Point","coordinates":[28.99619,-24.17584]},"id":"C23404733,NAVTEQ"},{"type":"Feature","properties":{"name":"Port St Johns","parent":"23401197,NAVTEQ","officialNames":{"en":"Port St Johns"}},"geometry":{"type":"Point","coordinates":[29.54528,-31.62335]},"id":"C23401432,NAVTEQ"},{"type":"Feature","properties":{"name":"King Sabata Dalindyebo","parent":"23401197,NAVTEQ","officialNames":{"en":"King Sabata Dalindyebo"}},"geometry":{"type":"Point","coordinates":[28.78844,-31.59225]},"id":"C23400867,NAVTEQ"},{"type":"Feature","properties":{"name":"Maphumulo","parent":"23402680,NAVTEQ","officialNames":{"en":"Maphumulo"}},"geometry":{"type":"Point","coordinates":[31.06795,-29.15999]},"id":"C23400286,NAVTEQ"},{"type":"Feature","properties":{"name":"KwaDukuza","parent":"23402680,NAVTEQ","officialNames":{"en":"KwaDukuza"}},"geometry":{"type":"Point","coordinates":[31.29453,-29.34697]},"id":"C23404015,NAVTEQ"},{"type":"Feature","properties":{"name":"Aganang","parent":"23400975,NAVTEQ","officialNames":{"en":"Aganang"}},"geometry":{"type":"Point","coordinates":[29.06021,-23.70928]},"id":"C23403899,NAVTEQ"},{"type":"Feature","properties":{"name":"Rustenburg","parent":"23399630,NAVTEQ","officialNames":{"en":"Rustenburg"}},"geometry":{"type":"Point","coordinates":[27.23578,-25.66399]},"id":"C23400086,NAVTEQ"},{"type":"Feature","properties":{"name":"Daveyton","parent":"23401975,NAVTEQ","officialNames":{"en":"Daveyton"}},"geometry":{"type":"Point","coordinates":[28.44029,-26.13211]},"id":"C23404496,NAVTEQ"},{"type":"Feature","properties":{"name":"Ngwathe","parent":"23399730,NAVTEQ","officialNames":{"en":"Ngwathe"}},"geometry":{"type":"Point","coordinates":[27.65598,-27.55399]},"id":"C23404161,NAVTEQ"},{"type":"Feature","properties":{"name":"Evaton","parent":"23404391,NAVTEQ","officialNames":{"en":"Evaton"}},"geometry":{"type":"Point","coordinates":[27.84829,-26.53011]},"id":"C23400109,NAVTEQ"},{"type":"Feature","properties":{"name":"Potchefstroom","parent":"23403718,NAVTEQ","officialNames":{"en":"Potchefstroom"}},"geometry":{"type":"Point","coordinates":[27.09805,-26.71467]},"id":"C23404493,NAVTEQ"},{"type":"Feature","properties":{"name":"Nkandla","parent":"23404478,NAVTEQ","officialNames":{"en":"Nkandla"}},"geometry":{"type":"Point","coordinates":[31.05877,-28.59143]},"id":"C23403618,NAVTEQ"},{"type":"Feature","properties":{"name":"Mbombela","parent":"23401768,NAVTEQ","officialNames":{"de":"Mbombela","fr":"Mbombela","en":"Mbombela","it":"Mbombela","es":"Mbombela","nl":"Mbombela"}},"geometry":{"type":"Point","coordinates":[30.9767,-25.47301]},"id":"C23400307,NAVTEQ"},{"type":"Feature","properties":{"name":"Thembisile","parent":"23403238,NAVTEQ","officialNames":{"en":"Thembisile"}},"geometry":{"type":"Point","coordinates":[28.89424,-25.40508]},"id":"C23402672,NAVTEQ"},{"type":"Feature","properties":{"name":"Lekwa","parent":"23402535,NAVTEQ","officialNames":{"en":"Lekwa"}},"geometry":{"type":"Point","coordinates":[28.93606,-26.79693]},"id":"C23575887,NAVTEQ"},{"type":"Feature","properties":{"name":"Ulundi","parent":"23403294,NAVTEQ","officialNames":{"en":"Ulundi"}},"geometry":{"type":"Point","coordinates":[31.42608,-28.29414]},"id":"C23737350,NAVTEQ"},{"type":"Feature","properties":{"name":"Drakenstein","parent":"23403169,NAVTEQ","officialNames":{"en":"Drakenstein"}},"geometry":{"type":"Point","coordinates":[18.97997,-33.71344]},"id":"C23404946,NAVTEQ"},{"type":"Feature","properties":{"name":"Senqu","parent":"23399635,NAVTEQ","officialNames":{"en":"Senqu"}},"geometry":{"type":"Point","coordinates":[27.5936,-30.96866]},"id":"C23401702,NAVTEQ"},{"type":"Feature","properties":{"name":"Mangaung","parent":"23401075,NAVTEQ","officialNames":{"en":"Mangaung"}},"geometry":{"type":"Point","coordinates":[26.25255,-29.16427]},"id":"C23400194,NAVTEQ"},{"type":"Feature","properties":{"name":"Kungwini","parent":"23404341,NAVTEQ","officialNames":{"en":"Kungwini"}},"geometry":{"type":"Point","coordinates":[28.74683,-25.81045]},"id":"C23401780,NAVTEQ"},{"type":"Feature","properties":{"name":"Roodepoort","parent":"23401543,NAVTEQ","officialNames":{"en":"Roodepoort"}},"geometry":{"type":"Point","coordinates":[27.86928,-26.16006]},"id":"C23402048,NAVTEQ"},{"type":"Feature","properties":{"name":"Moses Kotane","parent":"23399630,NAVTEQ","officialNames":{"en":"Moses Kotane"}},"geometry":{"type":"Point","coordinates":[26.61715,-25.49502]},"id":"C23400192,NAVTEQ"},{"type":"Feature","properties":{"name":"Mandeni","parent":"23402680,NAVTEQ","officialNames":{"en":"Mandeni"}},"geometry":{"type":"Point","coordinates":[31.4842,-29.10913]},"id":"C23400181,NAVTEQ"},{"type":"Feature","properties":{"name":"Mnquma","parent":"23401323,NAVTEQ","officialNames":{"en":"Mnquma"}},"geometry":{"type":"Point","coordinates":[28.15009,-32.32733]},"id":"C23401048,NAVTEQ"},{"type":"Feature","properties":{"name":"Newcastle","parent":"23400249,NAVTEQ","officialNames":{"en":"Newcastle"}},"geometry":{"type":"Point","coordinates":[29.93034,-27.75627]},"id":"C23400645,NAVTEQ"},{"type":"Feature","properties":{"name":"Setsoto","parent":"23401250,NAVTEQ","officialNames":{"en":"Setsoto"}},"geometry":{"type":"Point","coordinates":[27.88002,-28.87552]},"id":"C23399986,NAVTEQ"},{"type":"Feature","properties":{"name":"The Msunduzi","parent":"23404131,NAVTEQ","officialNames":{"en":"The Msunduzi"}},"geometry":{"type":"Point","coordinates":[30.37812,-29.60076]},"id":"C23400380,NAVTEQ"},{"type":"Feature","properties":{"name":"Boksburg","parent":"23401975,NAVTEQ","officialNames":{"en":"Boksburg"}},"geometry":{"type":"Point","coordinates":[28.25314,-26.22204]},"id":"C23403325,NAVTEQ"},{"type":"Feature","properties":{"name":"Okhahlamba","parent":"23404765,NAVTEQ","officialNames":{"en":"Okhahlamba"}},"geometry":{"type":"Point","coordinates":[29.52722,-28.81629]},"id":"C23738748,NAVTEQ"},{"type":"Feature","properties":{"name":"Tswaing","parent":"23403531,NAVTEQ","officialNames":{"en":"Tswaing"}},"geometry":{"type":"Point","coordinates":[25.45746,-26.68861]},"id":"C23402614,NAVTEQ"},{"type":"Feature","properties":{"name":"Ekurhuleni","parent":"23401975,NAVTEQ","officialNames":{"en":"Ekurhuleni"}},"geometry":{"type":"Point","coordinates":[28.15915,-26.2104]},"id":"C23399676,NAVTEQ"},{"type":"Feature","properties":{"name":"Mbizana","parent":"23401197,NAVTEQ","officialNames":{"en":"Mbizana"}},"geometry":{"type":"Point","coordinates":[29.85429,-30.85885]},"id":"C23402176,NAVTEQ"},{"type":"Feature","properties":{"name":"Indaka","parent":"23404765,NAVTEQ","officialNames":{"en":"Indaka"}},"geometry":{"type":"Point","coordinates":[30.08764,-28.51585]},"id":"C23402367,NAVTEQ"},{"type":"Feature","properties":{"name":"Sandton","parent":"23402002,NAVTEQ","officialNames":{"en":"Sandton"}},"geometry":{"type":"Point","coordinates":[28.05375,-26.10789]},"id":"C23405656,NAVTEQ"},{"type":"Feature","properties":{"name":"Nkonkobe","parent":"23401323,NAVTEQ","officialNames":{"en":"Nkonkobe"}},"geometry":{"type":"Point","coordinates":[26.62784,-32.7799]},"id":"C23404328,NAVTEQ"},{"type":"Feature","properties":{"name":"uMshwathi","parent":"23404131,NAVTEQ","officialNames":{"en":"uMshwathi"}},"geometry":{"type":"Point","coordinates":[30.46654,-29.34309]},"id":"C23404926,NAVTEQ"},{"type":"Feature","properties":{"name":"Mafikeng","parent":"23403531,NAVTEQ","officialNames":{"de":"Mafikeng","fr":"Mafikeng","en":"Mafikeng","it":"Mafikeng","es":"Mafikeng","nl":"Mafikeng"}},"geometry":{"type":"Point","coordinates":[25.64658,-25.86395]},"id":"C23404141,NAVTEQ"},{"type":"Feature","properties":{"name":"Albert Luthuli","parent":"23402535,NAVTEQ","officialNames":{"en":"Albert Luthuli"}},"geometry":{"type":"Point","coordinates":[30.11482,-26.06597]},"id":"C23403193,NAVTEQ"},{"type":"Feature","properties":{"name":"Mkhondo","parent":"23402535,NAVTEQ","officialNames":{"en":"Mkhondo"}},"geometry":{"type":"Point","coordinates":[30.80565,-27.01581]},"id":"C23403090,NAVTEQ"},{"type":"Feature","properties":{"name":"Etwatwa","parent":"23402002,NAVTEQ","officialNames":{"en":"Etwatwa"}},"geometry":{"type":"Point","coordinates":[28.46043,-26.11667]},"id":"C23405803,NAVTEQ"},{"type":"Feature","properties":{"name":"Ba-Phalaborwa","parent":"23404087,NAVTEQ","officialNames":{"en":"Ba-Phalaborwa"}},"geometry":{"type":"Point","coordinates":[31.03251,-23.93973]},"id":"C23404235,NAVTEQ"},{"type":"Feature","properties":{"name":"Dr J. S. Moroka","parent":"23403238,NAVTEQ","officialNames":{"en":"Dr J. S. Moroka"}},"geometry":{"type":"Point","coordinates":[28.85706,-25.1479]},"id":"C23401412,NAVTEQ"},{"type":"Feature","properties":{"name":"Imbabazane","parent":"23404765,NAVTEQ","officialNames":{"en":"Imbabazane"}},"geometry":{"type":"Point","coordinates":[29.73848,-29.05668]},"id":"C23399825,NAVTEQ"},{"type":"Feature","properties":{"name":"Bushbuckridge","parent":"23401768,NAVTEQ","officialNames":{"en":"Bushbuckridge"}},"geometry":{"type":"Point","coordinates":[31.24863,-24.98168]},"id":"C23401557,NAVTEQ"},{"type":"Feature","properties":{"name":"Breede Valley","parent":"23403169,NAVTEQ","officialNames":{"en":"Breede Valley"}},"geometry":{"type":"Point","coordinates":[19.43872,-33.65044]},"id":"C23400028,NAVTEQ"},{"type":"Feature","properties":{"name":"Greater Taung","parent":"23404503,NAVTEQ","officialNames":{"en":"Greater Taung"}},"geometry":{"type":"Point","coordinates":[24.55384,-27.55699]},"id":"C23403315,NAVTEQ"},{"type":"Feature","properties":{"name":"Greater Letaba","parent":"23404087,NAVTEQ","officialNames":{"en":"Greater Letaba"}},"geometry":{"type":"Point","coordinates":[30.14133,-23.6907]},"id":"C23401886,NAVTEQ"},{"type":"Feature","properties":{"name":"Elundini","parent":"23399635,NAVTEQ","officialNames":{"en":"Elundini"}},"geometry":{"type":"Point","coordinates":[28.23599,-31.19435]},"id":"C23400753,NAVTEQ"},{"type":"Feature","properties":{"name":"Nyandeni","parent":"23401197,NAVTEQ","officialNames":{"en":"Nyandeni"}},"geometry":{"type":"Point","coordinates":[29.02724,-31.53958]},"id":"C23403121,NAVTEQ"},{"type":"Feature","properties":{"name":"Jozini","parent":"23402845,NAVTEQ","officialNames":{"en":"Jozini"}},"geometry":{"type":"Point","coordinates":[32.11481,-27.76001]},"id":"C23399761,NAVTEQ"},{"type":"Feature","properties":{"name":"Metsimaholo","parent":"23399730,NAVTEQ","officialNames":{"en":"Metsimaholo"}},"geometry":{"type":"Point","coordinates":[28.21081,-26.97746]},"id":"C23404455,NAVTEQ"},{"type":"Feature","properties":{"name":"Hibiscus Coast","parent":"23401290,NAVTEQ","officialNames":{"en":"Hibiscus Coast"}},"geometry":{"type":"Point","coordinates":[30.45279,-30.73937]},"id":"C23399818,NAVTEQ"},{"type":"Feature","properties":{"name":"Greater Marble Hall","parent":"23403425,NAVTEQ","officialNames":{"en":"Greater Marble Hall"}},"geometry":{"type":"Point","coordinates":[29.29627,-24.96911]},"id":"C23401168,NAVTEQ"},{"type":"Feature","properties":{"name":"Mhlontlo","parent":"23401197,NAVTEQ","officialNames":{"en":"Mhlontlo"}},"geometry":{"type":"Point","coordinates":[28.75382,-31.30729]},"id":"C23403571,NAVTEQ"},{"type":"Feature","properties":{"name":"Molemole","parent":"23400975,NAVTEQ","officialNames":{"en":"Molemole"}},"geometry":{"type":"Point","coordinates":[29.32683,-23.36652]},"id":"C23399766,NAVTEQ"},{"type":"Feature","properties":{"name":"Ratlou","parent":"23403531,NAVTEQ","officialNames":{"en":"Ratlou"}},"geometry":{"type":"Point","coordinates":[24.99508,-26.07818]},"id":"C23401067,NAVTEQ"},{"type":"Feature","properties":{"name":"East London","parent":"23401323,NAVTEQ","officialNames":{"en":"East London"}},"geometry":{"type":"Point","coordinates":[27.90403,-33.01544]},"id":"C23403573,NAVTEQ"},{"type":"Feature","properties":{"name":"uMhlathuze","parent":"23404478,NAVTEQ","officialNames":{"en":"uMhlathuze"}},"geometry":{"type":"Point","coordinates":[32.1041,-28.7829]},"id":"C23404315,NAVTEQ"},{"type":"Feature","properties":{"name":"Emfuleni","parent":"23404391,NAVTEQ","officialNames":{"en":"Emfuleni"}},"geometry":{"type":"Point","coordinates":[27.84092,-26.57746]},"id":"C23401606,NAVTEQ"},{"type":"Feature","properties":{"name":"uPhongolo","parent":"23403294,NAVTEQ","officialNames":{"en":"uPhongolo"}},"geometry":{"type":"Point","coordinates":[31.61628,-27.37848]},"id":"C23404599,NAVTEQ"},{"type":"Feature","properties":{"name":"Matjhabeng","parent":"23400546,NAVTEQ","officialNames":{"en":"Matjhabeng"}},"geometry":{"type":"Point","coordinates":[26.7338,-27.97898]},"id":"C23401076,NAVTEQ"},{"type":"Feature","properties":{"name":"Makhuduthamaga","parent":"23403425,NAVTEQ","officialNames":{"en":"Makhuduthamaga"}},"geometry":{"type":"Point","coordinates":[29.82345,-24.72933]},"id":"C23404192,NAVTEQ"},{"type":"Feature","properties":{"name":"Greater Tzaneen","parent":"23404087,NAVTEQ","officialNames":{"en":"Greater Tzaneen"}},"geometry":{"type":"Point","coordinates":[30.15877,-23.8277]},"id":"C23402073,NAVTEQ"},{"type":"Feature","properties":{"name":"Qaukeni","parent":"23401197,NAVTEQ","officialNames":{"en":"Qaukeni"}},"geometry":{"type":"Point","coordinates":[29.49392,-31.08028]},"id":"C23404194,NAVTEQ"},{"type":"Feature","properties":{"name":"Abaqulusi","parent":"23403294,NAVTEQ","officialNames":{"en":"Abaqulusi"}},"geometry":{"type":"Point","coordinates":[30.79497,-27.76725]},"id":"C23403301,NAVTEQ"},{"type":"Feature","properties":{"name":"Merafong City","parent":"23403718,NAVTEQ","officialNames":{"en":"Merafong City"}},"geometry":{"type":"Point","coordinates":[27.39489,-26.36309]},"id":"C23404199,NAVTEQ"},{"type":"Feature","properties":{"name":"Cape Town","parent":"23401233,NAVTEQ","officialNames":{"de":"Kapstadt","it":"Città del Capo","fi":"Kapkaupunki","pt":"Cidade do Cabo","sv":"Kapstaden","fr":"Le Cap","en":"Cape Town","es":"Ciudad del Cabo","nl":"Kaapstad"}},"geometry":{"type":"Point","coordinates":[18.42197,-33.9191]},"id":"C23402330,NAVTEQ"},{"type":"Feature","properties":{"name":"Roodepoort South","parent":"23402002,NAVTEQ","officialNames":{"en":"Roodepoort South"}},"geometry":{"type":"Point","coordinates":[27.87034,-26.20999]},"id":"C23405613,NAVTEQ"},{"type":"Feature","properties":{"name":"Stellenbosch","parent":"23403169,NAVTEQ","officialNames":{"en":"Stellenbosch"}},"geometry":{"type":"Point","coordinates":[18.86559,-33.93145]},"id":"C23404260,NAVTEQ"},{"type":"Feature","properties":{"name":"Buffalo City","parent":"23401323,NAVTEQ","officialNames":{"en":"Buffalo City"}},"geometry":{"type":"Point","coordinates":[27.75848,-32.94256]},"id":"C23402337,NAVTEQ"},{"type":"Feature","properties":{"name":"Msukaligwa","parent":"23402535,NAVTEQ","officialNames":{"en":"Msukaligwa"}},"geometry":{"type":"Point","coordinates":[29.98655,-26.52541]},"id":"C23399807,NAVTEQ"},{"type":"Feature","properties":{"name":"Umzumbe","parent":"23401290,NAVTEQ","officialNames":{"en":"Umzumbe"}},"geometry":{"type":"Point","coordinates":[30.34066,-30.46369]},"id":"C23403267,NAVTEQ"},{"type":"Feature","properties":{"name":"Blouberg","parent":"23400975,NAVTEQ","officialNames":{"en":"Blouberg"}},"geometry":{"type":"Point","coordinates":[29.13683,-23.28723]},"id":"C23400970,NAVTEQ"},{"type":"Feature","properties":{"name":"Hlabisa","parent":"23402845,NAVTEQ","officialNames":{"en":"Hlabisa"}},"geometry":{"type":"Point","coordinates":[32.19148,-28.19495]},"id":"C23403277,NAVTEQ"},{"type":"Feature","properties":{"name":"Umzimkhulu","parent":"23402283,NAVTEQ","officialNames":{"en":"Umzimkhulu"}},"geometry":{"type":"Point","coordinates":[29.93817,-30.26407]},"id":"C23399946,NAVTEQ"},{"type":"Feature","properties":{"name":"Nongoma","parent":"23403294,NAVTEQ","officialNames":{"en":"Nongoma"}},"geometry":{"type":"Point","coordinates":[31.71023,-27.90255]},"id":"C23404451,NAVTEQ"},{"type":"Feature","properties":{"name":"Steve Tshwete","parent":"23403238,NAVTEQ","officialNames":{"en":"Steve Tshwete"}},"geometry":{"type":"Point","coordinates":[29.45584,-25.76386]},"id":"C23402530,NAVTEQ"},{"type":"Feature","properties":{"name":"Emalahleni","parent":"23403238,NAVTEQ","officialNames":{"en":"Emalahleni"}},"geometry":{"type":"Point","coordinates":[29.21125,-25.87266]},"id":"C23400979,NAVTEQ"},{"type":"Feature","properties":{"name":"Sol Plaatjie","parent":"23401881,NAVTEQ","officialNames":{"en":"Sol Plaatjie"}},"geometry":{"type":"Point","coordinates":[24.76023,-28.73444]},"id":"C23400636,NAVTEQ"},{"type":"Feature","properties":{"name":"Nelson Mandela Bay","parent":"23403960,NAVTEQ","officialNames":{"en":"Nelson Mandela Bay"}},"geometry":{"type":"Point","coordinates":[25.46774,-33.80002]},"id":"C23404452,NAVTEQ"},{"type":"Feature","properties":{"name":"Pretoria","parent":"23402002,NAVTEQ","officialNames":{"de":"Pretoria","fr":"Pretoria","en":"Pretoria","it":"Pretoria","es":"Pretoria","nl":"Pretoria"}},"geometry":{"type":"Point","coordinates":[28.18763,-25.74587]},"id":"C23405641,NAVTEQ"},{"type":"Feature","properties":{"name":"Durban","parent":"23402002,NAVTEQ","officialNames":{"en":"Durban"}},"geometry":{"type":"Point","coordinates":[31.03512,-29.85574]},"id":"C23405620,NAVTEQ"},{"type":"Feature","properties":{"name":"Umzimvubu","parent":"23399800,NAVTEQ","officialNames":{"en":"Umzimvubu"}},"geometry":{"type":"Point","coordinates":[28.99368,-30.90126]},"id":"C23399971,NAVTEQ"}]}